[
  {
    "title": "[DS Defense Daily] 2026-01-30",
    "pdf_url": "https://stock.pstatic.net/stock-research/market/66/20260130_market_321878000.pdf",
    "date": "26.01.30",
    "summary": "[2026-01-30] [DS Defense Daily] 2026-01-30\n\n### 요약\n\n**1. 주요 내용**\n- 노르웨이 정부는 20억 달러 규모의 로켓포 공급업체로 한국 기업 한화를 선정.\n- 한화의 '천무' 시스템은 장거리 정밀 사격 능력을 제공하며, 500km 사거리를 가진 미사일을 포함.\n- 이번 계약은 노르웨이 국방력 강화를 위한 것으로, 2028년부터 2031년까지 실전 배치 예정.\n- 노르웨이 정부는 한화가 성능, 납기, 비용 측면에서 모든 요구 조건을 충족하는 유일한 공급업체라고 평가.\n\n**2. 계약 배경**\n- 유럽 국가들은 러시아의 드론 및 미사일 공격에 대응하기 위해 장거리 타격 능력 강화 필요성 인식.\n- 덴마크, 독일, 프랑스 등도 유사한 무기 시스템 도입 계획 중.\n- 노르웨이 국방부는 KNDS와 라인메탈 등 다른 경쟁 업체를 배제하고 한화를 선정.\n\n**3. 계약 의의**\n- 한화의 천무 시스템은 폴란드에서도 생산 중이며, 유럽 내 공급 안정성 강화.\n- 이번 계약은 록히드마틴, KNDS 등 미국, 유럽 업체들과의 경쟁 입찰에서 승리.\n- 빠른 납기, 합리적인 비용, 다양한 사거리의 탄약 운용 가능성 등이 성공 요인으로 평가.\n\n**4. 향후 전망**\n- 유럽 내 다른 국가들도 한화 천무 시스템 도입 가능성 증가.\n- 노르웨이를 시작으로 한화의 유럽 시장 확장 기대.",
    "category": "market"
  },
  {
    "title": "Yuanta Morning Snapshot (2026.01.30)",
    "pdf_url": "https://stock.pstatic.net/stock-research/market/18/20260130_market_308599000.pdf",
    "date": "26.01.30",
    "summary": "[2026-01-30] Yuanta Morning Snapshot (2026.01.30)\n\n### 리포트 요약\n\n#### 1. 글로벌 증시 추이\n- **미국 증시**: 다우(+0.11%), 나스닥(-0.72%), S&P500(-0.13%)\n  - **VIX**는 +3.24% 상승하며 변동성 증가\n  - **필라델피아 반도체**는 +0.16% 상승\n- **아시아 증시**:\n  - **일본(NIKKEI225)** +0.03%, **대만** -0.82%, **홍콩 항셍** +0.51%\n  - **상하이종합** +0.16%, **홍콩 H** +0.42%\n- **유럽 증시**:\n  - **영국(FTSE100)** +0.17%, **독일(DAX)** -2.07%\n- **신흥시장**:\n  - **MSCI 이머징** +1.83%, **인도** +0.27%\n\n#### 2. 증시 주변자금\n- **고객예탁금**: 103,362억원 (전주 대비 +3,573억원)\n- **기관 순매수**: 1,041억원 (전주 대비 +707억원)\n- **외국인 순매수**: 1,434.09억원 (전주 대비 +625억원)\n\n#### 3. 원자재 가격\n- **WTI**: +3.50% 상승, **금**: +0.01% 상승\n- **구리**: +0.62%, **밀**: +1.03% 상승\n\n#### 4. 환율 변화\n- **원/달러**: 1,301.5원 (전주 대비 +1.69원)\n- **원/엔**: 1,030.5원 (전주 대비 +0.15원)\n- **원/위안**: 190.5원 (전주 대비 +0.00원)\n\n#### 5. 주요 뉴스\n- **일본**: 도요타, 세계 자동차 판매 6년 연속 1위\n- **미국**: 트럼프, 금리 인하 압박에도 동결\n- **한국**: SK하이닉스 사상 최대 실적, 코스피 5200pt 돌파\n\n#### 6. 시장 리뷰\n- **코스피**: +0.98% 상승, SK하이닉스가 주도\n- **코스닥**: +1.00% 상승\n- **미국**: 다우지수는 혼조, 반도체주 강세\n- **중국**: 주가 과열 억제 방침에 혼조세\n\n#### 7. 주요 이벤트\n- **미국 이란 공습 우려**: 금값 상승\n- **젠슨 황 대만 방문**: 중국 H200 판매 허용 요청\n\n### 결론\n글로벌 증시는 혼조세를 보이며, 특히 미국 기술주들의 실적 발표가 시장에 영향을 미쳤다. 한국 증시도 강세를 보였으며, 원자재와 환율도 변동성을 보였다. 주요 경제 이벤트와 뉴스가 시장 흐름에 중요한 역할을 하고 있다.",
    "category": "market"
  },
  {
    "title": "[DS 시황 데일리] 현시점 2026-01-30",
    "pdf_url": "https://stock.pstatic.net/stock-research/market/66/20260130_market_616246000.pdf",
    "date": "26.01.30",
    "summary": "[2026-01-30] [DS 시황 데일리] 현시점 2026-01-30\n\n### 핵심 요약\n\n#### 1. 주식시장 동향\n- **코스피와 코스닥**: 전일 각각 1.0%, 2.7% 상승. 미국 빅테크 기업 실적 발표 후 변동성 확대.\n- **환율**: 엔/달러 152원대, 원/달러 1,420원대. 달러 약세 흐름 지속.\n- **외국인 투자**: SK하이닉스, 삼성전자 중심으로 1.5조원 순매도. 코스닥에서는 금융투자가 2조원 순매수.\n\n#### 2. 업종 이슈\n- **반도체**: 삼성전자, SK하이닉스 호실적 발표 후 변동성 확대. HBM 매출 3배 이상 증가 전망.\n- **원전**: AI 전력 인프라 관련 SMR(소형모듈원자로) 관련 주식 상승.\n- **로봇**: 테슬라 로봇 사업 개편 발표로 로봇 관련 주식 상승.\n- **자동차**: 현대오토에버, 현대차, 현대위아 등 상승.\n- **증권**: 고객예탁금 100조원 돌파, 거래대금 1,000조원 기록.\n\n#### 3. 주요 종목\n- **상승률 상위**:\n  - 1일: 한양이엔지(+12.5%), 한미반도체(+11.8%)\n  - 1주: 에코프로비엠(+7.4%), 에코프로(+2.0%)\n  - 1개월: SK텔레콤(+22.7%), 삼성전기(+37.9%)\n- **외국인/기관 순매수**:\n  - 외국인: SK하이닉스, 삼성전자\n  - 기관: SK증권, 미래에셋증권, 한국금융지주\n- **테마별**:\n  - AI, 로봇, 원전, 반도체, 제약/바이오 등 테마별 상승.\n\n#### 4. 기타\n- **신용융자잔고 및 고객예탁금**: 신용융자잔고 132.3조원, 고객예탁금 100조원 돌파.\n- **정부 정책**: 한국판 스타링크 구축을 위한 저궤도 위성 통신체계 구축 논의 본격화.",
    "category": "market"
  },
  {
    "title": "Daily Morning Brief(2026.01.30)",
    "pdf_url": "https://stock.pstatic.net/stock-research/market/76/20260130_market_693785000.pdf",
    "date": "26.01.30",
    "summary": "[2026-01-30] Daily Morning Brief(2026.01.30)\n\n**리포트 요약:**\n\n이 리포트는 금융 분석 관점에서 IT 산업의 최근 동향과 시장 전망을 다루고 있습니다. 주요 내용은 다음과 같습니다:\n\n1. **IT 산업의 성장 동력**:\n   - 디지털 전환 가속화\n   - 클라우드 컴퓨팅 및 AI 기술의 발전\n   - 사이버 보안 수요 증가\n\n2. **시장 트렌드**:\n   - 원격 근무 및 온라인 서비스의 확대로 인한 IT 솔루션 수요 증가\n   - ESG(환경, 사회, 지배구조) 투자 확대\n\n3. **주요 이슈**:\n   - 반도체 공급망 문제\n   - 인플레이션과 금리 인상이 IT 기업에 미치는 영향\n\n4. **투자 전략**:\n   - 클라우드 서비스 제공업체와 사이버 보안 기업에 대한 긍정적 전망\n   - 지속 가능한 기술(Green Tech) 관련 기업에 주목\n\n5. **리스크 요인**:\n   - 글로벌 경제 불확실성과 지정학적 리스크\n   - 기술 규제 강화 가능성\n\n이 리포트는 IT 산업의 기회와 도전 과제를 종합적으로 분석하여 투자자와 기업 전략 수립에 유용한 정보를 제공합니다.",
    "category": "market"
  },
  {
    "title": "Daily Morning Brief(2026.01.29)",
    "pdf_url": "https://stock.pstatic.net/stock-research/market/76/20260130_market_988767000.pdf",
    "date": "26.01.30",
    "summary": "[2026-01-30] Daily Morning Brief(2026.01.29)\n\n리포트 요약:\n\n이 리포트는 다양한 국가의 금융 및 경제 관련 정보를 다루고 있습니다. 주요 내용은 다음과 같습니다:\n\n- **미국(US)**:\n  - 여러 금융 및 경제 관련 문서 링크 제공\n  - IT 산업 동향 및 시장 분석 자료 포함\n\n- **이탈리아(Italy)**:\n  - 경제 지표 및 산업 동향 관련 자료 링크\n  - 금융 시장 및 정책 관련 정보\n\n- **한국(Korea)**:\n  - 청(靑) 관련 경제 정책 및 이슈 분석\n  - 다양한 금융 시장 동향 및 보고서 링크\n\n- **IT 산업**:\n  - 글로벌 IT 시장 트렌드 및 기업 분석 자료\n  - 기술 혁신과 금융의 융합에 대한 논의\n\n각 섹션은 관련 링크들을 통해 심층적인 자료 접근을 가능하게 하며, 특히 미국과 이탈리아의 경제 및 금융 시장에 대한 상세한 분석이 포함되어 있습니다.",
    "category": "market"
  },
  {
    "title": "SK증권 아침에 슥_2026.01.30",
    "pdf_url": "https://stock.pstatic.net/stock-research/market/64/20260130_market_971708000.pdf",
    "date": "26.01.30",
    "summary": "[2026-01-30] SK증권 아침에 슥_2026.01.30\n\n### 리포트 요약\n\n#### 1. 주요 지수 및 시장 동향\n- **국내 시장**:\n  - KOSPI: 5,221.25, 1D +1.0%, 1M +23.9%, YTD +105.8%\n  - KOSDAQ: 1,164.41, 1D +2.7%, 1M +25.8%, YTD +59.8%\n  - 개인 순매수 약 1조 6천억원, 코스피 5,200 안착\n- **글로벌 시장**:\n  - 미국 S&P 500: 4,233.75, 1D -1.2%, 1M +11.1%, YTD +8.6%\n  - 유럽, 중국 등 주요국 지수는 혼조세\n  - AI 회의론, 테크 기업 실적 부진, 지정학적 리스크 등으로 변동성 확대\n\n#### 2. 주요 이슈\n- **AI 회의론**: MS, 메타 실적 발표 후 AI 관련 기술주 약세\n- **지정학적 리스크**: 이란 공격 위협, 미국-이란 긴장 고조\n- **주가 과열**: 중국 당국의 주가 과열 억제 방침에 따른 기술주 매도\n\n#### 3. 섹터별 성과\n- **IT하드웨어**: 인텔리안테크, LG이노텍 등 상승\n- **디스플레이**: 삼성디스플레이, LG디스플레이 하락\n- **운송**: 대한항공, 아시아나항공 등 하락\n- **철강**: POSCO, 현대제철 등 상승\n- **화장품**: LG생활건강, 아모레퍼시픽 등 상승\n\n#### 4. 주요 종목\n- **상승률 상위**: 인텔리안테크, 대한광통신, 흥구석유 등\n- **하락률 상위**: 하이드로리튬, 브이엠, 미코 등\n- **순매수 강도**: 인텔리안테크, 대한광통신, 흥구석유 등\n\n#### 5. 글로벌 시장 동향\n- **미국**: 생산자물가지수, GDP 발표 예정\n- **유럽**: 독일 GDP 발표\n- **중국**: 소매판매 지표 발표\n- **금리**: 미국채 10년, 독일 국채 10년 등 주요 금리 변동\n\n#### 6. 투자 환경\n- **리스크 요인**: AI 회의론, 지정학적 리스크, 주가 과열 우려\n- **기회 요인**: 개인 투자자 매수세, 특정 섹터(IT하드웨어, 철강 등)의 상대적 강세\n\n**결론**: 현재 시장은 AI 회의론과 지정학적 리스크로 인한 변동성 확대 국면에 있으며, 특정 섹터와 종목에 대한 선별적 접근이 필요합니다. 투자자는 리스크 관리와 함께 시장 흐름을 주의 깊게 관찰해야 합니다.",
    "category": "market"
  },
  {
    "title": "AI 과잉투자 우려 확대되며 미 증시 혼조 마감",
    "pdf_url": "https://stock.pstatic.net/stock-research/market/61/20260130_market_967162000.pdf",
    "date": "26.01.30",
    "summary": "[2026-01-30] AI 과잉투자 우려 확대되며 미 증시 혼조 마감\n\n### 요약\n\n**국내 증시**\n- KOSPI는 +0.98%, KOSDAQ은 +2.73% 상승 마감.\n- 삼성전자 실적 발표로 인한 변동성 확대, 증권 및 이차전지 업종 강세.\n- 삼성전자, SK하이닉스의 실적 발표 후 차익실현 매물 출회.\n\n**해외 증시**\n- 미국 증시 혼조 마감: AI 과잉투자 우려로 마이크로소프트(-9.99%), 오라클(-2.23%) 등 하락.\n- 메타(+10.40%)는 실적 호조로 급등.\n- 엔비디아, ASML 등 반도체주 상승, 필라델피아 반도체 지수 +0.16% 상승.\n\n**주요 이슈**\n- AI 과잉투자 우려로 인한 빅테크 실적 발표 후 주가 변동.\n- 삼성전자 사상 최대 실적 발표 후 차익실현 매물 출회.\n- 국내 증시, 최근 빠른 상승에 따른 단기 조정 가능성 존재.\n\n**경제 지표**\n- 한국 12월 소매판매, 산업생산 발표 예정.\n- 일본 1월 소비자물가 발표 예정.\n- 미국 11월 소매판매, 12월 산업생산 등 주요 지표 발표 예정.\n\n**환율**\n- 달러-원 환율 1,426.30원 기록.\n\n**기타**\n- MSCI 한국 ETF는 -0.84% 약보합 마감.\n- 글로벌 ETF 중 QQQ(-0.6%), VWO(-0.4%) 하락, TLT(0.0%), VNQ(1.4%) 상승.",
    "category": "market"
  },
  {
    "title": "[IBKS Daily] Morning Brief(260130)",
    "pdf_url": "https://stock.pstatic.net/stock-research/market/40/20260130_market_577574000.pdf",
    "date": "26.01.30",
    "summary": "[2026-01-30] [IBKS Daily] Morning Brief(260130)\n\n**국내 증시 요약**\n\n- **KOSPI**는 1.0% 상승하여 5,221.3P로 마감, **KOSDAQ**은 2.7% 상승하여 1,164.4P로 마감.\n- **달러 가치 하락 진정**: FOMC의 매파적 해석과 베선트 재무장관의 강달러 정책 재확인 영향으로 원달러 환율은 3.8원 상승.\n- **삼성전자, SK하이닉스**가 사상 최대 분기 실적을 발표하며 오후장 상승 전환, 양 시장 모두 신고가 기록.\n- **기획예산처**는 2026년 기금 자산운용 기본방향에서 코스닥 지수를 기금평가 기준수익률에 일부 반영하기로 결정.\n\n**주요 종목 및 업종 동향**\n\n- **현대오토에버**: 9.8% 상승, 주당 1,900원 결산 배당 결정.\n- **에코프로비엠**: 7.4% 상승, 52주 신고가 경신하며 코스닥 시가총액 1위 탈환.\n- **LG화학**: 3.1% 하락, 2026년 매출 목표를 전년 대비 낮은 23조원으로 제시.\n- **업종 수익률**:\n  - **IT**: 9.2% 상승\n  - **필수소비재**: 5.0% 상승\n  - **건강관리**: 13.9% 상승\n  - **소재**: 11.5% 상승\n  - **금융**: 6.9% 상승\n\n**투자 동향**\n\n- **코스피**는 대형주 1.0%, 중형주 1.1%, 소형주 1.2% 상승.\n- **코스닥**는 대형주 3.5%, 중형주 2.3%, 소형주 1.6% 상승.\n- **외국인**, **기관**, **개인** 투자자 모두 코스피와 코스닥에서 매수 우위 기록.",
    "category": "market"
  },
  {
    "title": "SK증권 Global Carbon Market Daily_260130",
    "pdf_url": "https://stock.pstatic.net/stock-research/market/64/20260130_market_726613000.pdf",
    "date": "26.01.30",
    "summary": "[2026-01-30] SK증권 Global Carbon Market Daily_260130\n\n### 글로벌 배출권 가격 요약\n\n#### 주요 배출권 가격 동향\n- **EUA (유럽연합 배출권)**: 84.0 유로/톤, 3개월 기준 4.2% 상승\n- **UKA (영국 배출권)**: 65.1 파운드/톤, 3개월 기준 7.3% 상승\n- **RGGI (미국 동북부 배출권)**: 24.9 달러/톤, 3개월 기준 5.0% 하락\n- **CCA (캐나다 배출권)**: 30.4 달러/톤, 3개월 기준 10.0% 하락\n- **KAU (한국 배출권)**: 12,550 원/톤, 3개월 기준 20.7% 상승\n- **KOC/i-KOC (국내 배출권)**: 11,000/12,400 원/톤, 3개월 기준 안정\n- **중국 CEA**: 78.5 위안/톤, 3개월 기준 51.1% 상승\n\n#### 탄소배출권 ETF/ETN 동향\n- **KRBN, KEUA, KCCA, GRN**: 3개월 기준 2.4~7.3% 하락\n- **KRW 기반 ETF/ETN**: 3개월 기준 1.1~2.4% 하락\n\n### 글로벌 에너지 가격 요약\n- **원유(WTI)**: 3개월 기준 12.9% 상승\n- **천연가스(NYM HH)**: 3개월 기준 11.9% 하락\n- **유럽 전력 가격(ICE Dutch TTF)**: 3개월 기준 44.5% 상승\n- **LNG**: 3개월 기준 19.8% 상승\n\n### 주요 뉴스\n- **미국/유럽 원유 가격 상승**: 이란 근해 미군 집결로 WTI 3.5% 상승\n- **한국탄소배출권산업협회 출범**: 배출권 시장 정보 체계 구축\n- **NDC 감축 이행안 수립**: 2035년 목표 반영\n- **탄소배출권 ETF/ETN 하락**: 시장 변동성 확대\n\n### 그래프 요약\n- **배출권 가격**: KAU, EUA 상승, RGGI, CCA 하락\n- **에너지 가격**: WTI 상승, 천연가스 하락, 전력 가격 급등\n- **배출권 ETF**: 대부분 하락세 유지\n\n**참고**: 3개월(3M) 기준 변동률 및 가격 흐름 분석.",
    "category": "market"
  },
  {
    "title": "[Market Odds] 1월 5주차",
    "pdf_url": "https://stock.pstatic.net/stock-research/market/64/20260130_market_124700000.pdf",
    "date": "26.01.30",
    "summary": "[2026-01-30] [Market Odds] 1월 5주차\n\n### 핵심 요약\n\n**1. 예측시장 동향**\n- **거래량**: 예측시장 거래량은 상승세를 유지하고 있으며, 1월 FOMC 종료 후 잠시 소강 상태 예상. 그러나 전반적인 견조한 추세는 지속될 것으로 보임.\n- **미국 중간선거**: 중간선거 관련 민감도 증가 예상. 셧다운 재발 가능성은 50% 정도로 하락.\n- **연준 의장**: 릭 리더가 차기 연준 의장 선두주자. 월러에 대한 베팅 증가. 지명 시점은 2월 중순~말로 예상.\n\n**2. 주요 예측시장 지표**\n- **주간 거래량**: 주요 예측시장의 주간 거래량이 지속적으로 증가하고 있음.\n- **주간 거래 횟수 및 이용자 수**: 거래 횟수와 이용자 수 역시 상승세를 보이고 있음.\n- **TPV (Total Platform Value)**: Polymarket과 Opinion의 TPV가 꾸준히 증가하고 있음.\n\n**3. 주요 예측사항**\n- **연방대법원 판결**: 트럼프에게 유리한 판결 가능성 38.3% (Vol: 3.83M).\n- **셧다운 가능성**: 18.6% (Vol: 18.60M).\n- **그린란드 취득**: 완전 취득 25.8% (Vol: 25.77M), 부분 취득 7.0% (Vol: 7.05M).\n- **연준 정책**: 3월 FOMC에서 기준금리 25bp 인하 가능성 8.9% (Vol: 8.86M).\n- **미국 경기침체**: 190.4% (Vol: 190.4K).\n- **트럼프 지명 시점**: 527.9K (Vol: 527.92K).\n- **AI 및 기술**: AI 버블 붕괴 1.9% (Vol: 1.89M), GPT-6 출시 32.0% (Vol: 32.00M).\n\n**4. 정치적/경제적 이슈**\n- **중간선거**: 하원 및 상원 다수당 관련 예측.\n- **경제**: 미국 경기침체 가능성, 연준 정책 변화.\n- **기술**: AI 모델 보유 기업, 테슬라 FSD 출시 등.\n\n**5. 주요 시장 참여자 관심**\n- 연준 의장 지명, 미국 정치 상황, AI 및 기술 혁신, 경제 지표 등이 주요 관심사로 부각.",
    "category": "market"
  },
  {
    "title": "DAILY RECAP_2026.01.30",
    "pdf_url": "https://stock.pstatic.net/stock-research/market/64/20260130_market_212655000.pdf",
    "date": "26.01.30",
    "summary": "[2026-01-30] DAILY RECAP_2026.01.30\n\n**리포트 요약 (2026-01-30)**\n\n- **변동성**: 전일 Pre-market 변동성이 0.034 상승하여, 이는 오전 중 지수 하방 압력으로 작용할 가능성이 높습니다.\n- **외국인 수급**: 환율, 금리, 글로벌 위험선호도를 고려했을 때, 금일 외국인은 차익 실현이나 관망할 가능성이 큽니다.\n- **투자 전략**: 업종별 수익률 분산과 외국인 수급 여건을 종합하면, 금일 종목 선택 중심의 알파 전략이 상대적으로 유리할 것으로 판단됩니다.",
    "category": "market"
  },
  {
    "title": "1/30 KB 리서치 모닝코멘트",
    "pdf_url": "https://stock.pstatic.net/stock-research/market/58/20260130_market_690210000.pdf",
    "date": "26.01.30",
    "summary": "[2026-01-30] 1/30 KB 리서치 모닝코멘트\n\n### 핵심 요약\n\n#### 1. **미국 증시 동향**\n- **혼조세**: MS의 AI 수익성 우려와 연방정부 셧다운 가능성에도 불구하고 저가 매수세 유입으로 낙폭 제한.\n- **주요 종목**:\n  - **MS**: AI 투자 비용 과잉 지출 우려로 약 10% 하락.\n  - **메타 플랫폼스**: 강력한 매출 전망 제시로 10%대 급등.\n  - **애플**: 아이폰 17 판매 호조 소식에 시간외 상승.\n- **지수 변화**:\n  - **S&P 500**: -0.1%\n  - **NASDAQ**: -0.7%\n  - **Dow Jones**: 0.1%\n\n#### 2. **글로벌 증시 동향**\n- **중국**: 증시 과열 경계감과 차익 실현 매도로 혼조세 (상해 +0.16%).\n- **유럽**: 글로벌 빅테크 실적 실망감에 혼조세 (DAX -2%).\n- **기타**:\n  - **홍콩 항셍**: +0.5%\n  - **일본 니케이225**: +0.0%\n\n#### 3. **FICC 시장 동향**\n- **채권**:\n  - 미국 10년 국채 수익률: 4.23% (-1.2bp)\n  - 달러 인덱스: 96.18 (-0.27%)\n- **상품**:\n  - WTI 유가: 65.42달러/배럴 (+3.50%) - 이란 대규모 공습 소식\n  - 금: 5,318.4달러 (+0.3%)\n\n#### 4. **주간 증시 캘린더**\n- **26일(월)**: 삼성에피스홀딩스, S-Oil 실적 발표\n- **27일(화)**: LS ELECTRIC, 유나이티드헬스그룹, UPS, GM, 보잉 실적 발표\n- **29일(목)**: FOMC 회의\n- **30일(금)**: 하나금융지주, 애플 실적 발표\n\n#### 5. **투자 전략**\n- **주의점**:\n  - MS의 AI 투자 비용 문제, 글로벌 빅테크 실적 실망감\n  - 유가 상승 요인 (이란 공습)\n- **기회**:\n  - 메타 플랫폼스의 강력한 매출 전망\n  - 애플의 아이폰 17 판매 호조\n\n### 결론\n미국 및 글로벌 증시는 다양한 요인들로 인해 혼조세를 보이고 있으며, 특히 AI 관련 기업들의 실적과 전망이 중요한 변수로 작용하고 있습니다. 투자자들은 이러한 변수들을 주시하며, 개별 기업의 실적 발표와 경제 지표에 따른 시장 변동성을 고려해야 합니다.",
    "category": "market"
  },
  {
    "title": "1/29 KB 리서치 장마감코멘트",
    "pdf_url": "https://stock.pstatic.net/stock-research/market/58/20260130_market_241481000.pdf",
    "date": "26.01.30",
    "summary": "[2026-01-30] 1/29 KB 리서치 장마감코멘트\n\n### 요약\n\n**리포트 주요 내용:**\n- **KB증권의 자료 신뢰성:** 본 자료는 기관투자가나 제3자에게 제공되지 않았으며, 작성자는 해당 종목과 재산적 이해관계가 없습니다. 외부 압력 없이 작성되었음을 확인했습니다.\n- **투자 경고:** 이 보고서는 투자 판단의 법적 근거가 되지 않으며, KB증권의 의견이나 정보의 정확성을 보장하지 않습니다.\n- **시장 상황:**\n  - **KOSPI**는 5,221pt (+0.98%), **KOSDAQ**는 1,164pt (+2.73%)로 마감.\n  - **반도체 투톱**(삼성전자, SK하이닉스)의 호실적이 투자 심리를 지지하며 랠리가 연장됨.\n  - **연준의 금리 인하 속도 조절**로 시장 영향은 제한적.\n  - **삼성전자**는 1.3조원 특별배당 발표, **SK하이닉스**는 대규모 자사주 소각 계획 발표.\n- **매매 동향:**\n  - **KOSPI**에서 개인은 1.6조원 순매수, 외국인은 2조원 넘게 순매도.\n  - **KOSDAQ**에서는 기관이 2조원 순매수.\n  - **에코프로비엠**과 **에코프로**가 KOSDAQ 시가총액 1, 2위를 탈환.\n- **기타:**\n  - **현대차**는 미 관세에도 불구하고 사상 최대 매출 기록.\n  - **미 증시**는 애플 실적 발표를 앞두고 반도체 중심으로 강세.\n  - **다음 주 주요 실적 발표:** LG전자, 삼성중공업, 현대로템 등.\n\n**투자 지표:**\n- KOSPI P/E 10.88배, P/B 1.68배\n- 고객예탁금 100.28조원, 신용잔고 29.25조원\n\n**주요 종목 매매 동향:**\n- KOSPI: 두산에너빌리티(+1,727억원), 현대차(+1,390억원)\n- KOSDAQ: 에코프로(+1,108억원), 에코프로비엠(+641억원)\n\n**향후 일정:**\n- 1월 30일: 삼성에피스홀딩스, S-Oil, LG이노텍, 유니드 실적 발표\n- 2월 1일: 11월 FHFA 주택가격지수, 11월 S&P CS 주택가격지수 (미국)\n- 2월 2일: 1월 리치몬드 연방 제조업지수, 1월 컨퍼런스보드 소비자기대지수 (미국)\n- 2월 3일: 애플 실적 발표 예정 (미국)",
    "category": "market"
  }
]